mandelviews/__init__.py
mandelviews/core.py
mandelviews/mandelviews_legacy.py
mandelviews/version.py
mandelviews/vis.py
mandelviews-0.0.3.dev18.dist-info/LICENSE
mandelviews-0.0.3.dev18.dist-info/METADATA
mandelviews-0.0.3.dev18.dist-info/WHEEL
mandelviews-0.0.3.dev18.dist-info/top_level.txt
mandelviews-0.0.3.dev18.dist-info/RECORD
