Metadata-Version: 2.1
Name: mandelviews
Version: 0.0.3.dev18
Summary: Create and view mandelbrot sets, following guidelines in ccn template.
Author-email: Eric Thomson <thomson.eric@gmail.com>
License: MIT License
Project-URL: Homepage, https://github.com/EricThomson/mandelviews
Classifier: Programming Language :: Python :: 3
Classifier: License :: OSI Approved :: MIT License
Classifier: Operating System :: OS Independent
Requires-Python: >=3.8
License-File: LICENSE
Requires-Dist: numpy
Requires-Dist: matplotlib
Requires-Dist: PyQt5
Provides-Extra: dev
Requires-Dist: black ; extra == 'dev'
Requires-Dist: isort ; extra == 'dev'
Requires-Dist: pytest ; extra == 'dev'
Requires-Dist: flake8 ; extra == 'dev'
Requires-Dist: pytest-cov ; extra == 'dev'
Requires-Dist: pydocstyle ; extra == 'dev'
Provides-Extra: docs
Requires-Dist: mkdocs ; extra == 'docs'
Requires-Dist: mkdocstrings[python] ; extra == 'docs'
Requires-Dist: mkdocs-section-index ; extra == 'docs'
Requires-Dist: mkdocs-gen-files ; extra == 'docs'
Requires-Dist: mkdocs-literate-nav ; extra == 'docs'
Requires-Dist: mkdocs-gallery ; extra == 'docs'
